{
  "index_futures": [
    {
      "symbol": "NIFTY",
      "name": "Nifty 50"
    },
    {
      "symbol": "BANKNIFTY",
      "name": "Nifty BANK"
    },
    {
      "symbol": "FINNIFTY",
      "name": "Nifty FINANCIAL SERVICES"
    },
    {
      "symbol": "MIDCPNIFTY",
      "name": "Nifty MIDCAP SELECT"
    },
    {
      "symbol": "NIFTYNXT50",
      "name": "Nifty NEXT 50"
    }
  ],
  "individual_securities": [
    {
      "symbol": "PIIND",
      "name": "PI Industries Limited"
    },
    {
      "symbol": "AARTIIND",
      "name": "Aarti Industries Limited"
    },
    {
      "symbol": "INOXWIND",
      "name": "Inox Wind Limited"
    },
    {
      "symbol": "LAURUSLABS",
      "name": "Laurus Labs Limited"
    },
    {
      "symbol": "DIXON",
      "name": "Dixon Technologies (India) Limited"
    },
    {
      "symbol": "DEEPAKNTR",
      "name": "Deepak Nitrite Limited"
    },
    {
      "symbol": "SRF",
      "name": "SRF Limited"
    },
    {
      "symbol": "HINDALCO",
      "name": "Hindalco Industries Limited"
    },
    {
      "symbol": "PNBHOUSING",
      "name": "PNB Housing Finance Limited"
    },
    {
      "symbol": "JSL",
      "name": "Jindal Stainless Limited"
    },
    {
      "symbol": "SONACOMS",
      "name": "Sona BLW Precision Forgings Limited"
    },
    {
      "symbol": "APOLLOTYRE",
      "name": "Apollo Tyres Limited"
    },
    {
      "symbol": "JSWSTEEL",
      "name": "JSW Steel Limited"
    },
    {
      "symbol": "TATASTEEL",
      "name": "Tata Steel Limited"
    },
    {
      "symbol": "HDFCAMC",
      "name": "HDFC Asset Management Company Limited"
    },
    {
      "symbol": "MOTHERSON",
      "name": "Samvardhana Motherson International Limited"
    },
    {
      "symbol": "COALINDIA",
      "name": "Coal India Limited"
    },
    {
      "symbol": "GRANULES",
      "name": "Granules India Limited"
    },
    {
      "symbol": "POLICYBZR",
      "name": "PB Fintech Limited"
    },
    {
      "symbol": "UPL",
      "name": "UPL Limited"
    },
    {
      "symbol": "PATANJALI",
      "name": "Patanjali Foods Limited"
    },
    {
      "symbol": "JIOFIN",
      "name": "Jio Financial Services Limited"
    },
    {
      "symbol": "PRESTIGE",
      "name": "Prestige Estates Projects Limited"
    },
    {
      "symbol": "KPITTECH",
      "name": "KPIT Technologies Limited"
    },
    {
      "symbol": "MCX",
      "name": "Multi Commodity Exchange of India Limited"
    },
    {
      "symbol": "GRASIM",
      "name": "Grasim Industries Limited"
    },
    {
      "symbol": "DIVISLAB",
      "name": "Divi's Laboratories Limited"
    },
    {
      "symbol": "SOLARINDS",
      "name": "Solar Industries India Limited"
    },
    {
      "symbol": "HAVELLS",
      "name": "Havells India Limited"
    },
    {
      "symbol": "CGPOWER",
      "name": "CG Power and Industrial Solutions Limited"
    },
    {
      "symbol": "ADANIGREEN",
      "name": "Adani Green Energy Limited"
    },
    {
      "symbol": "POONAWALLA",
      "name": "Poonawalla Fincorp Limited"
    },
    {
      "symbol": "MRF",
      "name": "MRF Limited"
    },
    {
      "symbol": "ONGC",
      "name": "Oil & Natural Gas Corporation Limited"
    },
    {
      "symbol": "CAMS",
      "name": "Computer Age Management Services Limited"
    },
    {
      "symbol": "ADANIENT",
      "name": "Adani Enterprises Limited"
    },
    {
      "symbol": "POWERGRID",
      "name": "Power Grid Corporation of India Limited"
    },
    {
      "symbol": "TRENT",
      "name": "Trent Limited"
    },
    {
      "symbol": "BHARATFORG",
      "name": "Bharat Forge Limited"
    },
    {
      "symbol": "BIOCON",
      "name": "Biocon Limited"
    },
    {
      "symbol": "PAYTM",
      "name": "One 97 Communications Limited"
    },
    {
      "symbol": "ABFRL",
      "name": "Aditya Birla Fashion and Retail Limited"
    },
    {
      "symbol": "PAGEIND",
      "name": "Page Industries Limited"
    },
    {
      "symbol": "TATATECH",
      "name": "Tata Technologies Limited"
    },
    {
      "symbol": "OBEROIRLTY",
      "name": "Oberoi Realty Limited"
    },
    {
      "symbol": "HINDZINC",
      "name": "Hindustan Zinc Limited"
    },
    {
      "symbol": "PERSISTENT",
      "name": "Persistent Systems Limited"
    },
    {
      "symbol": "SAIL",
      "name": "Steel Authority of India Limited"
    },
    {
      "symbol": "M&M",
      "name": "Mahindra & Mahindra Limited"
    },
    {
      "symbol": "RECLTD",
      "name": "REC Limited"
    },
    {
      "symbol": "CIPLA",
      "name": "Cipla Limited"
    },
    {
      "symbol": "SBILIFE",
      "name": "SBI Life Insurance Company Limited"
    },
    {
      "symbol": "LTIM",
      "name": "LTIMindtree Limited"
    },
    {
      "symbol": "NTPC",
      "name": "NTPC Limited"
    },
    {
      "symbol": "RELIANCE",
      "name": "Reliance Industries Limited"
    },
    {
      "symbol": "APLAPOLLO",
      "name": "APL Apollo Tubes Limited"
    },
    {
      "symbol": "KALYANKJIL",
      "name": "Kalyan Jewellers India Limited"
    },
    {
      "symbol": "KOTAKBANK",
      "name": "Kotak Mahindra Bank Limited"
    },
    {
      "symbol": "NMDC",
      "name": "NMDC Limited"
    },
    {
      "symbol": "MGL",
      "name": "Mahanagar Gas Limited"
    },
    {
      "symbol": "BAJAJ-AUTO",
      "name": "Bajaj Auto Limited"
    },
    {
      "symbol": "ZYDUSLIFE",
      "name": "Zydus Lifesciences Limited"
    },
    {
      "symbol": "INDHOTEL",
      "name": "The Indian Hotels Company Limited"
    },
    {
      "symbol": "CHOLAFIN",
      "name": "Cholamandalam Investment and Finance Company Limited"
    },
    {
      "symbol": "ADANIPORTS",
      "name": "Adani Ports and Special Economic Zone Limited"
    },
    {
      "symbol": "BAJAJFINSV",
      "name": "Bajaj Finserv Limited"
    },
    {
      "symbol": "LUPIN",
      "name": "Lupin Limited"
    },
    {
      "symbol": "BHARTIARTL",
      "name": "Bharti Airtel Limited"
    },
    {
      "symbol": "OFSS",
      "name": "Oracle Financial Services Software Limited"
    },
    {
      "symbol": "JINDALSTEL",
      "name": "Jindal Steel & Power Limited"
    },
    {
      "symbol": "RBLBANK",
      "name": "RBL Bank Limited"
    },
    {
      "symbol": "VEDL",
      "name": "Vedanta Limited"
    },
    {
      "symbol": "BALKRISIND",
      "name": "Balkrishna Industries Limited"
    },
    {
      "symbol": "AUROPHARMA",
      "name": "Aurobindo Pharma Limited"
    },
    {
      "symbol": "JSWENERGY",
      "name": "JSW Energy Limited"
    },
    {
      "symbol": "TATACHEM",
      "name": "Tata Chemicals Limited"
    },
    {
      "symbol": "CANBK",
      "name": "Canara Bank"
    },
    {
      "symbol": "MPHASIS",
      "name": "MphasiS Limited"
    },
    {
      "symbol": "HDFCBANK",
      "name": "HDFC Bank Limited"
    },
    {
      "symbol": "CESC",
      "name": "CESC Limited"
    },
    {
      "symbol": "TATAMOTORS",
      "name": "Tata Motors Limited"
    },
    {
      "symbol": "NAUKRI",
      "name": "Info Edge (India) Limited"
    },
    {
      "symbol": "OIL",
      "name": "Oil India Limited"
    },
    {
      "symbol": "ETERNAL",
      "name": "ETERNAL LIMITED"
    },
    {
      "symbol": "MARICO",
      "name": "Marico Limited"
    },
    {
      "symbol": "SUNPHARMA",
      "name": "Sun Pharmaceutical Industries Limited"
    },
    {
      "symbol": "ASHOKLEY",
      "name": "Ashok Leyland Limited"
    },
    {
      "symbol": "ATGL",
      "name": "Adani Total Gas Limited"
    },
    {
      "symbol": "LT",
      "name": "Larsen & Toubro Limited"
    },
    {
      "symbol": "INDUSINDBK",
      "name": "IndusInd Bank Limited"
    },
    {
      "symbol": "TITAGARH",
      "name": "TITAGARH RAIL SYSTEMS LIMITED"
    },
    {
      "symbol": "PEL",
      "name": "Piramal Enterprises Limited"
    },
    {
      "symbol": "CDSL",
      "name": "Central Depository Services (India) Limited"
    },
    {
      "symbol": "SHRIRAMFIN",
      "name": "Shriram Finance Limited"
    },
    {
      "symbol": "BAJFINANCE",
      "name": "Bajaj Finance Limited"
    },
    {
      "symbol": "PFC",
      "name": "Power Finance Corporation Limited"
    },
    {
      "symbol": "IRCTC",
      "name": "Indian Railway Catering And Tourism Corporation Limited"
    },
    {
      "symbol": "TORNTPOWER",
      "name": "Torrent Power Limited"
    },
    {
      "symbol": "TITAN",
      "name": "Titan Company Limited"
    },
    {
      "symbol": "BANDHANBNK",
      "name": "Bandhan Bank Limited"
    },
    {
      "symbol": "TATAPOWER",
      "name": "Tata Power Company Limited"
    },
    {
      "symbol": "BEL",
      "name": "Bharat Electronics Limited"
    },
    {
      "symbol": "GAIL",
      "name": "GAIL (India) Limited"
    },
    {
      "symbol": "NBCC",
      "name": "NBCC (India) Limited"
    },
    {
      "symbol": "ABB",
      "name": "ABB India Limited"
    },
    {
      "symbol": "HAL",
      "name": "Hindustan Aeronautics Limited"
    },
    {
      "symbol": "IREDA",
      "name": "Indian Renewable Energy Development Agency Limited"
    },
    {
      "symbol": "ABCAPITAL",
      "name": "Aditya Birla Capital Limited"
    },
    {
      "symbol": "SUPREMEIND",
      "name": "Supreme Industries Limited"
    },
    {
      "symbol": "DLF",
      "name": "DLF Limited"
    },
    {
      "symbol": "NYKAA",
      "name": "FSN E-Commerce Ventures Limited"
    },
    {
      "symbol": "BPCL",
      "name": "Bharat Petroleum Corporation Limited"
    },
    {
      "symbol": "UNITDSPR",
      "name": "United Spirits Limited"
    },
    {
      "symbol": "TVSMOTOR",
      "name": "TVS Motor Company Limited"
    },
    {
      "symbol": "BSE",
      "name": "BSE Limited"
    },
    {
      "symbol": "M&MFIN",
      "name": "Mahindra & Mahindra Financial Services Limited"
    },
    {
      "symbol": "SJVN",
      "name": "SJVN Limited"
    },
    {
      "symbol": "WIPRO",
      "name": "Wipro Limited"
    },
    {
      "symbol": "ESCORTS",
      "name": "Escorts Kubota Limited"
    },
    {
      "symbol": "SBIN",
      "name": "State Bank of India"
    },
    {
      "symbol": "EICHERMOT",
      "name": "Eicher Motors Limited"
    },
    {
      "symbol": "POLYCAB",
      "name": "Polycab India Limited"
    },
    {
      "symbol": "DRREDDY",
      "name": "Dr. Reddy's Laboratories Limited"
    },
    {
      "symbol": "DELHIVERY",
      "name": "Delhivery Limited"
    },
    {
      "symbol": "CROMPTON",
      "name": "Crompton Greaves Consumer Electricals Limited"
    },
    {
      "symbol": "HEROMOTOCO",
      "name": "Hero MotoCorp Limited"
    },
    {
      "symbol": "HINDCOPPER",
      "name": "Hindustan Copper Limited"
    },
    {
      "symbol": "ITC",
      "name": "ITC Limited"
    },
    {
      "symbol": "HUDCO",
      "name": "Housing & Urban Development Corporation Limited"
    },
    {
      "symbol": "ANGELONE",
      "name": "Angel One Limited"
    },
    {
      "symbol": "INDIANB",
      "name": "Indian Bank"
    },
    {
      "symbol": "LTF",
      "name": "L&T Finance Limited"
    },
    {
      "symbol": "MARUTI",
      "name": "Maruti Suzuki India Limited"
    },
    {
      "symbol": "HFCL",
      "name": "HFCL Limited"
    },
    {
      "symbol": "IDEA",
      "name": "Vodafone Idea Limited"
    },
    {
      "symbol": "NCC",
      "name": "NCC Limited"
    },
    {
      "symbol": "CHAMBLFERT",
      "name": "Chambal Fertilizers & Chemicals Limited"
    },
    {
      "symbol": "SYNGENE",
      "name": "Syngene International Limited"
    },
    {
      "symbol": "VBL",
      "name": "Varun Beverages Limited"
    },
    {
      "symbol": "BANKINDIA",
      "name": "Bank of India"
    },
    {
      "symbol": "IDFCFIRSTB",
      "name": "IDFC First Bank Limited"
    },
    {
      "symbol": "EXIDEIND",
      "name": "Exide Industries Limited"
    },
    {
      "symbol": "UNIONBANK",
      "name": "Union Bank of India"
    },
    {
      "symbol": "HCLTECH",
      "name": "HCL Technologies Limited"
    },
    {
      "symbol": "ALKEM",
      "name": "Alkem Laboratories Limited"
    },
    {
      "symbol": "TATACONSUM",
      "name": "TATA CONSUMER PRODUCTS LIMITED"
    },
    {
      "symbol": "INFY",
      "name": "Infosys Limited"
    },
    {
      "symbol": "IRFC",
      "name": "Indian Railway Finance Corporation Limited"
    },
    {
      "symbol": "ACC",
      "name": "ACC Limited"
    },
    {
      "symbol": "BANKBARODA",
      "name": "Bank of Baroda"
    },
    {
      "symbol": "ULTRACEMCO",
      "name": "UltraTech Cement Limited"
    },
    {
      "symbol": "TECHM",
      "name": "Tech Mahindra Limited"
    },
    {
      "symbol": "CUMMINSIND",
      "name": "Cummins India Limited"
    },
    {
      "symbol": "IEX",
      "name": "Indian Energy Exchange Limited"
    },
    {
      "symbol": "LODHA",
      "name": "Macrotech Developers Limited"
    },
    {
      "symbol": "ICICIBANK",
      "name": "ICICI Bank Limited"
    },
    {
      "symbol": "BOSCHLTD",
      "name": "Bosch Limited"
    },
    {
      "symbol": "TIINDIA",
      "name": "Tube Investments of India Limited"
    },
    {
      "symbol": "AXISBANK",
      "name": "Axis Bank Limited"
    },
    {
      "symbol": "INDUSTOWER",
      "name": "Indus Towers Limited"
    },
    {
      "symbol": "VOLTAS",
      "name": "Voltas Limited"
    },
    {
      "symbol": "BSOFT",
      "name": "BIRLASOFT LIMITED"
    },
    {
      "symbol": "SBICARD",
      "name": "SBI Cards and Payment Services Limited"
    },
    {
      "symbol": "HINDPETRO",
      "name": "Hindustan Petroleum Corporation Limited"
    },
    {
      "symbol": "ADANIENSOL",
      "name": "Adani Energy Solutions Limited"
    },
    {
      "symbol": "TATACOMM",
      "name": "Tata Communications Limited"
    },
    {
      "symbol": "HINDUNILVR",
      "name": "Hindustan Unilever Limited"
    },
    {
      "symbol": "AUBANK",
      "name": "AU Small Finance Bank Limited"
    },
    {
      "symbol": "BHEL",
      "name": "Bharat Heavy Electricals Limited"
    },
    {
      "symbol": "PIDILITIND",
      "name": "Pidilite Industries Limited"
    },
    {
      "symbol": "NESTLEIND",
      "name": "Nestle India Limited"
    },
    {
      "symbol": "LICI",
      "name": "Life Insurance Corporation Of India"
    },
    {
      "symbol": "LICHSGFIN",
      "name": "LIC Housing Finance Limited"
    },
    {
      "symbol": "SIEMENS",
      "name": "Siemens Limited"
    },
    {
      "symbol": "MANAPPURAM",
      "name": "Manappuram Finance Limited"
    },
    {
      "symbol": "PNB",
      "name": "Punjab National Bank"
    },
    {
      "symbol": "GLENMARK",
      "name": "Glenmark Pharmaceuticals Limited"
    },
    {
      "symbol": "NATIONALUM",
      "name": "National Aluminium Company Limited"
    },
    {
      "symbol": "JUBLFOOD",
      "name": "Jubilant Foodworks Limited"
    },
    {
      "symbol": "KEI",
      "name": "KEI Industries Limited"
    },
    {
      "symbol": "TORNTPHARM",
      "name": "Torrent Pharmaceuticals Limited"
    },
    {
      "symbol": "FEDERALBNK",
      "name": "The Federal Bank  Limited"
    },
    {
      "symbol": "IOC",
      "name": "Indian Oil Corporation Limited"
    },
    {
      "symbol": "AMBUJACEM",
      "name": "Ambuja Cements Limited"
    },
    {
      "symbol": "BRITANNIA",
      "name": "Britannia Industries Limited"
    },
    {
      "symbol": "HDFCLIFE",
      "name": "HDFC Life Insurance Company Limited"
    },
    {
      "symbol": "YESBANK",
      "name": "Yes Bank Limited"
    },
    {
      "symbol": "MFSL",
      "name": "Max Financial Services Limited"
    },
    {
      "symbol": "TATAELXSI",
      "name": "Tata Elxsi Limited"
    },
    {
      "symbol": "COFORGE",
      "name": "Coforge Limited"
    },
    {
      "symbol": "NHPC",
      "name": "NHPC Limited"
    },
    {
      "symbol": "TCS",
      "name": "Tata Consultancy Services Limited"
    },
    {
      "symbol": "IGL",
      "name": "Indraprastha Gas Limited"
    },
    {
      "symbol": "RAMCOCEM",
      "name": "The Ramco Cements Limited"
    },
    {
      "symbol": "DMART",
      "name": "Avenue Supermarts Limited"
    },
    {
      "symbol": "CYIENT",
      "name": "Cyient Limited"
    },
    {
      "symbol": "CONCOR",
      "name": "Container Corporation of India Limited"
    },
    {
      "symbol": "GMRAIRPORT",
      "name": "GMR AIRPORTS LIMITED"
    },
    {
      "symbol": "APOLLOHOSP",
      "name": "Apollo Hospitals Enterprise Limited"
    },
    {
      "symbol": "IIFL",
      "name": "IIFL Finance Limited"
    },
    {
      "symbol": "PETRONET",
      "name": "Petronet LNG Limited"
    },
    {
      "symbol": "INDIGO",
      "name": "InterGlobe Aviation Limited"
    },
    {
      "symbol": "COLPAL",
      "name": "Colgate Palmolive (India) Limited"
    },
    {
      "symbol": "ASIANPAINT",
      "name": "Asian Paints Limited"
    },
    {
      "symbol": "DALBHARAT",
      "name": "Dalmia Bharat Limited"
    },
    {
      "symbol": "DABUR",
      "name": "Dabur India Limited"
    },
    {
      "symbol": "SHREECEM",
      "name": "SHREE CEMENT LIMITED"
    },
    {
      "symbol": "PHOENIXLTD",
      "name": "The Phoenix Mills Limited"
    },
    {
      "symbol": "IRB",
      "name": "IRB Infrastructure Developers Limited"
    },
    {
      "symbol": "GODREJCP",
      "name": "Godrej Consumer Products Limited"
    },
    {
      "symbol": "GODREJPROP",
      "name": "Godrej Properties Limited"
    },
    {
      "symbol": "BERGEPAINT",
      "name": "Berger Paints (I) Limited"
    },
    {
      "symbol": "ASTRAL",
      "name": "Astral Limited"
    },
    {
      "symbol": "MAXHEALTH",
      "name": "Max Healthcare Institute Limited"
    },
    {
      "symbol": "ICICIPRULI",
      "name": "ICICI Prudential Life Insurance Company Limited"
    },
    {
      "symbol": "ICICIGI",
      "name": "ICICI Lombard General Insurance Company Limited"
    },
    {
      "symbol": "MUTHOOTFIN",
      "name": "Muthoot Finance Limited"
    }
  ]
}